qiscus_sdk/__init__.py
qiscus_sdk/cli.py
qiscus_sdk/qiscus_sdk.py
qiscus_sdk-0.1.1.dist-info/DESCRIPTION.rst
qiscus_sdk-0.1.1.dist-info/METADATA
qiscus_sdk-0.1.1.dist-info/RECORD
qiscus_sdk-0.1.1.dist-info/WHEEL
qiscus_sdk-0.1.1.dist-info/entry_points.txt
qiscus_sdk-0.1.1.dist-info/metadata.json
qiscus_sdk-0.1.1.dist-info/top_level.txt
