Metadata-Version: 2.0
Name: qiscus-sdk
Version: 0.1.1
Summary: Python version of Qiscus SDK wrapper
Home-page: https://github.com/nurulishlah/qiscus_sdk
Author: Muhamad Ishlah
Author-email: nurul.ishlah@gmail.com
License: MIT license
Keywords: qiscus_sdk qiscus sdk
Platform: UNKNOWN
Classifier: Development Status :: 2 - Pre-Alpha
Classifier: Intended Audience :: Developers
Classifier: License :: OSI Approved :: MIT License
Classifier: Natural Language :: English
Classifier: Programming Language :: Python :: 2
Classifier: Programming Language :: Python :: 2.6
Classifier: Programming Language :: Python :: 2.7
Classifier: Programming Language :: Python :: 3
Classifier: Programming Language :: Python :: 3.3
Classifier: Programming Language :: Python :: 3.4
Classifier: Programming Language :: Python :: 3.5
Requires-Dist: Click (>=6.0)
Requires-Dist: certifi (==2017.4.17)
Requires-Dist: chardet (==3.0.3)
Requires-Dist: idna (==2.5)
Requires-Dist: requests (==2.17.3)
Requires-Dist: urllib3 (==1.21.1)
